celegans/__init__.py
celegans/analytics.py
celegans/distributions.py
celegans/driver.py
celegans/exploitation.py
celegans/graph_stat.py
celegans/search.py
celegans/statistics.py
celegans/transforms.py
celegans/utilities.py
celegans-0.0.1.dist-info/DESCRIPTION.rst
celegans-0.0.1.dist-info/METADATA
celegans-0.0.1.dist-info/RECORD
celegans-0.0.1.dist-info/WHEEL
celegans-0.0.1.dist-info/metadata.json
celegans-0.0.1.dist-info/top_level.txt
