Metadata-Version: 2.0
Name: celegans
Version: 0.0.1
Summary: CELEGANS Network Toolbox
Home-page: https://github.com/iscoe/celegans
Author: Joseph Downs
Author-email: joseph.downs@jhuapl.edu
License: UNKNOWN
Download-URL: https://github.com/iscoe/celegans/archive/0.0.1.tar.gz
Keywords: brain,graph,network
Platform: UNKNOWN
